{
    "title": "Day 5: 忙しい日常と未来の計画 (바쁜 일상과 미래의 계획)",
    "story": "<h3>Scene 1. 朝のハプニング (아침의 해프닝)</h3><p><ruby>最近<rt>さいきん</rt></ruby>、可愛い<ruby>子猫<rt>こねこ</rt></ruby>を飼い始めました。しかし、<ruby>今夜<rt>こんや</rt></ruby>までに仕上げる<ruby>作品<rt>さくひん</rt></ruby>があって忙しいです。朝、食事の<ruby>支度<rt>したく</rt></ruby>をしている時に<ruby>失敗<rt>しっぱい</rt></ruby>しました。<ruby>米<rt>こめ</rt></ruby>を洗っていると、<ruby>魚屋<rt>さかなや</rt></ruby>で買った魚を猫が狙っていました。慌てて<ruby>砂糖<rt>さとう</rt></ruby>をこぼしてしまい、<ruby>室内<rt>しつない</rt></ruby>が<ruby>ごみ<rt>ごみ</rt></ruby>だらけになりました。熱いスープで<ruby>舌<rt>した</rt></ruby>をやけどし、汚れた<ruby>下着<rt>したぎ</rt></ruby>を着替えることになりました。</p><h3>Scene 2. 変わりゆく街 (변해가는 거리)</h3><p>家を出て、<ruby>この辺<rt>このへん</rt></ruby>の急な<ruby>坂<rt>さか</rt></ruby>を下りました。<ruby>市<rt>し</rt></ruby>の中心へ向かう途中、<ruby>自動車<rt>じどうしゃ</rt></ruby>と<ruby>自転車<rt>じてんしゃ</rt></ruby>の軽い<ruby>事故<rt>じこ</rt></ruby>を見ました。まるで<ruby>地震<rt>じしん</rt></ruby>のように大きな音がしました。<ruby>自動<rt>じどう</rt></ruby>ドアのバスに乗って<ruby>市内<rt>しない</rt></ruby>を眺めると、<ruby>桜<rt>さくら</rt></ruby>は散って<ruby>木の葉<rt>このは</rt></ruby>が舞っていました。<ruby>時代<rt>じだい</rt></ruby>と共に、この街の<ruby>産業<rt>さんぎょう</rt></ruby>も変わっています。「<ruby>失礼<rt>しつれい</rt></ruby>します」と言って、私は席に座りました。</p><h3>Scene 3. 学校での授業 (학교 수업)</h3><p>私は学校で<ruby>算数<rt>さんすう</rt></ruby>を教えています。<ruby>今回<rt>こんかい</rt></ruby>の<ruby>試験<rt>しけん</rt></ruby>には、<ruby>三角<rt>さんかく</rt></ruby>形の面積の問題が出ました。生徒から「先生、この<ruby>字<rt>じ</rt></ruby>の意味を<ruby>辞典<rt>じてん</rt></ruby>で調べてもいいですか」と<ruby>質問<rt>しつもん</rt></ruby>がありました。私は「そのやり<ruby>方<rt>かた</rt></ruby>(<ruby>仕方<rt>しかた</rt></ruby>)でいいですよ」と<ruby>賛成<rt>さんせい</rt></ruby>しました。<ruby>この間<rt>このあいた</rt></ruby>教えたことを、みんなよく覚えていました。</p><h3>Scene 4. 未来の予定 (미래의 예정)</h3><p><ruby>今度<rt>こんど</rt></ruby>の日曜日はサッカーの<ruby>試合<rt>しあい</rt></ruby>を見に行きます。楽しみな予定がたくさんあります。<ruby>再来週<rt>さらいしゅう</rt></ruby>は旅行に行き、<ruby>再来月<rt>さらいげつ</rt></ruby>は友人の結婚式です。そして、<ruby>再来年<rt>さらいねん</rt></ruby>には新しい家に引っ越すつもりです。</p>",
    "analysis": [
        {
            "sent": "<ruby>最近<rt>さいきん</rt></ruby>、可愛い<ruby>子猫<rt>こねこ</rt></ruby>を飼い始めました。",
            "trans": "최근, 귀여운 아기 고양이를 기르기 시작했습니다.",
            "grammar": "동사 마스형 + 始める: ~하기 시작하다.",
            "tags": [
                "最近",
                "子猫"
            ]
        },
        {
            "sent": "しかし、<ruby>今夜<rt>こんや</rt></ruby>までに仕上げる<ruby>作品<rt>さくひん</rt></ruby>があって忙しいです。",
            "trans": "하지만, 오늘 밤까지 완성해야 하는 작품이 있어서 바쁩니다.",
            "grammar": "~までに: ~까지 (기한) / ~て (이유): ~해서.",
            "tags": [
                "今夜",
                "作品"
            ]
        },
        {
            "sent": "朝、食事の<ruby>支度<rt>したく</rt></ruby>をしている時に<ruby>失敗<rt>しっぱい</rt></ruby>しました。",
            "trans": "아침, 식사 준비를 하고 있을 때 실수했습니다.",
            "grammar": "~している時に: ~하고 있을 때 (진행 중인 시점).",
            "tags": [
                "支度",
                "失敗"
            ]
        },
        {
            "sent": "<ruby>米<rt>こめ</rt></ruby>を洗っていると、<ruby>魚屋<rt>さかなや</rt></ruby>で買った魚を猫が狙っていました。",
            "trans": "쌀을 씻고 있는데, 생선 가게에서 산 생선을 고양이가 노리고 있었습니다.",
            "grammar": "~と (계기): ~하고 있으니 (뒤에 사건 발생).",
            "tags": [
                "米",
                "魚屋"
            ]
        },
        {
            "sent": "慌てて<ruby>砂糖<rt>さとう</rt></ruby>をこぼしてしまい、<ruby>室内<rt>しつない</rt></ruby>が<ruby>ごみ<rt>ごみ</rt></ruby>だらけになりました。",
            "trans": "당황해서 설탕을 쏟아 버려, 실내가 쓰레기투성이가 되었습니다.",
            "grammar": "~てしまう (완료/유감): ~해 버리다 / 명사 + だらけ: ~투성이.",
            "tags": [
                "砂糖",
                "室内",
                "ごみ"
            ]
        },
        {
            "sent": "熱いスープで<ruby>舌<rt>した</rt></ruby>をやけどし、汚れた<ruby>下着<rt>したぎ</rt></ruby>を着替えることになりました。",
            "trans": "뜨거운 수프에 혀를 데고, 더러워진 속옷을 갈아입게 되었습니다.",
            "grammar": "~ことになる: ~하게 되다 (결과/상황의 변화).",
            "tags": [
                "舌",
                "下着"
            ]
        },
        {
            "sent": "家を出て、<ruby>この辺<rt>このへん</rt></ruby>の急な<ruby>坂<rt>さか</rt></ruby>を下りました。",
            "trans": "집을 나서서, 이 근처의 급한 언덕을 내려갔습니다.",
            "grammar": "場所 + を + 移動動詞: 장소를 ~하다 (건너다, 지나다 등).",
            "tags": [
                "この辺",
                "坂"
            ]
        },
        {
            "sent": "<ruby>市<rt>し</rt></ruby>の中心へ向かう途中、<ruby>自動車<rt>じどうしゃ</rt></ruby>と<ruby>自転車<rt>じてんしゃ</rt></ruby>の軽い<ruby>事故<rt>じこ</rt></ruby>を見ました。",
            "trans": "시의 중심으로 향하는 도중, 자동차와 자전거의 가벼운 접촉 사고를 보았습니다.",
            "grammar": "동사 기본형 + 途中(とちゅう): ~하는 도중.",
            "tags": [
                "市",
                "自動車",
                "自転車",
                "事故"
            ]
        },
        {
            "sent": "まるで<ruby>地震<rt>じしん</rt></ruby>のように大きな音がしました。",
            "trans": "마치 지진처럼 큰 소리가 났습니다.",
            "grammar": "まるで + 명사 + のように: 마치 ~처럼 (비유).",
            "tags": [
                "地震"
            ]
        },
        {
            "sent": "<ruby>自動<rt>じどう</rt></ruby>ドアのバスに乗って<ruby>市内<rt>しない</rt></ruby>を眺めると、<ruby>桜<rt>さくら</rt></ruby>は散って<ruby>木の葉<rt>このは</rt></ruby>が舞っていました。",
            "trans": "자동문 버스를 타고 시내를 바라보니, 벚꽃은 지고 나뭇잎이 흩날리고 있었습니다.",
            "grammar": "~と (발견): ~하니 (~임을 알았다).",
            "tags": [
                "自動",
                "市内",
                "桜",
                "木の葉"
            ]
        },
        {
            "sent": "<ruby>時代<rt>じだい</rt></ruby>と共に、この街の<ruby>産業<rt>さんぎょう</rt></ruby>も変わっています。",
            "trans": "시대와 함께, 이 거리의 산업도 변하고 있습니다.",
            "grammar": "명사 + と共に(とともに): ~와 함께, ~에 따라서.",
            "tags": [
                "時代",
                "産業"
            ]
        },
        {
            "sent": "「<ruby>失礼<rt>しつれい</rt></ruby>します」と言って、私は席に座りました。",
            "trans": "'실례합니다'라고 말하고, 저는 자리에 앉았습니다.",
            "grammar": "~と言って: ~라고 말하고.",
            "tags": [
                "失礼"
            ]
        },
        {
            "sent": "私は学校で<ruby>算数<rt>さんすう</rt></ruby>を教えています。",
            "trans": "저는 학교에서 산수를 가르치고 있습니다.",
            "grammar": "~ています (직업/상태): ~하고 있다.",
            "tags": [
                "算数"
            ]
        },
        {
            "sent": "<ruby>今回<rt>こんかい</rt></ruby>の<ruby>試験<rt>しけん</rt></ruby>には、<ruby>三角<rt>さんかく</rt></ruby>形の面積の問題が出ました。",
            "trans": "이번 시험에는 삼각형의 면적 문제가 나왔습니다.",
            "grammar": "명사 + には: ~에는.",
            "tags": [
                "今回",
                "試験",
                "三角"
            ]
        },
        {
            "sent": "生徒から「先生、この<ruby>字<rt>じ</rt></ruby>の意味を<ruby>辞典<rt>じてん</rt></ruby>で調べてもいいですか」と<ruby>質問<rt>しつもん</rt></ruby>がありました。",
            "trans": "학생으로부터 '선생님, 이 글자의 의미를 사전에서 찾아봐도 됩니까?'라는 질문이 있었습니다.",
            "grammar": "~てもいいですか (허가): ~해도 됩니까?",
            "tags": [
                "字",
                "辞典",
                "質問"
            ]
        },
        {
            "sent": "私は「そのやり<ruby>方<rt>かた</rt></ruby>(<ruby>仕方<rt>しかた</rt></ruby>)でいいですよ」と<ruby>賛成<rt>さんせい</rt></ruby>しました。",
            "trans": "저는 '그 방식(방법)으로 해도 좋아요'라고 찬성했습니다.",
            "grammar": "동사 마스형 + 方(かた): ~하는 법.",
            "tags": [
                "仕方",
                "賛成"
            ]
        },
        {
            "sent": "<ruby>この間<rt>このあいた</rt></ruby>教えたことを、みんなよく覚えていました。",
            "trans": "요전에 가르친 것을, 모두 잘 기억하고 있었습니다.",
            "grammar": "동사 과거형 + ことを: ~한 것을.",
            "tags": [
                "この間"
            ]
        },
        {
            "sent": "<ruby>今度<rt>こんど</rt></ruby>の日曜日はサッカーの<ruby>試合<rt>しあい</rt></ruby>を見に行きます。",
            "trans": "이번(다가오는) 일요일은 축구 시합을 보러 갑니다.",
            "grammar": "동사 마스형 + に行く: ~하러 가다 (목적).",
            "tags": [
                "今度",
                "試合"
            ]
        },
        {
            "sent": "<ruby>再来週<rt>さらいしゅう</rt></ruby>は旅行に行き、<ruby>再来月<rt>さらいげつ</rt></ruby>は友人の結婚式です。",
            "trans": "다다음 주는 여행을 가고, 다다음 달은 친구의 결혼식입니다.",
            "grammar": "명사 + で (중지법): ~이고 (문장 연결).",
            "tags": [
                "再来週",
                "再来月"
            ]
        },
        {
            "sent": "そして、<ruby>再来年<rt>さらいねん</rt></ruby>には新しい家に引っ越すつもりです。",
            "trans": "그리고, 내후년에는 새집으로 이사할 생각입니다.",
            "grammar": "동사 기본형 + つもりです: ~할 생각/작정입니다 (의지).",
            "tags": [
                "再来年"
            ]
        }
    ],
    "vocab": [
        {
            "word": "子猫",
            "read": "こねこ",
            "mean": "아기 고양이"
        },
        {
            "word": "この間",
            "read": "このあいた",
            "mean": "요전, 일전"
        },
        {
            "word": "木の葉",
            "read": "このは",
            "mean": "나뭇잎"
        },
        {
            "word": "この辺",
            "read": "このへん",
            "mean": "이 근처"
        },
        {
            "word": "ごみ",
            "read": "ごみ",
            "mean": "쓰레기"
        },
        {
            "word": "米",
            "read": "こめ",
            "mean": "쌀"
        },
        {
            "word": "今回",
            "read": "こんかい",
            "mean": "이번"
        },
        {
            "word": "今度",
            "read": "こんど",
            "mean": "이번, 다음"
        },
        {
            "word": "今夜",
            "read": "こんや",
            "mean": "오늘 밤"
        },
        {
            "word": "最近",
            "read": "さいきん",
            "mean": "최근"
        },
        {
            "word": "坂",
            "read": "さか",
            "mean": "언덕"
        },
        {
            "word": "魚屋",
            "read": "さかなや",
            "mean": "생선 가게"
        },
        {
            "word": "作品",
            "read": "さくひん",
            "mean": "작품"
        },
        {
            "word": "桜",
            "read": "さくら",
            "mean": "벚꽃"
        },
        {
            "word": "砂糖",
            "read": "さとう",
            "mean": "설탕"
        },
        {
            "word": "再来月",
            "read": "さらいげつ",
            "mean": "다다음 달"
        },
        {
            "word": "再来週",
            "read": "さらいしゅう",
            "mean": "다다음 주"
        },
        {
            "word": "再来年",
            "read": "さらいねん",
            "mean": "내후년"
        },
        {
            "word": "三角",
            "read": "さんかく",
            "mean": "삼각"
        },
        {
            "word": "産業",
            "read": "さんぎょう",
            "mean": "산업"
        },
        {
            "word": "算数",
            "read": "さんすう",
            "mean": "산수"
        },
        {
            "word": "賛成",
            "read": "さんせい",
            "mean": "찬성"
        },
        {
            "word": "市",
            "read": "し",
            "mean": "시"
        },
        {
            "word": "字",
            "read": "じ",
            "mean": "글자"
        },
        {
            "word": "試合",
            "read": "しあい",
            "mean": "시합"
        },
        {
            "word": "仕方",
            "read": "しかた",
            "mean": "방법"
        },
        {
            "word": "試験",
            "read": "しけん",
            "mean": "시험"
        },
        {
            "word": "事故",
            "read": "じこ",
            "mean": "사고"
        },
        {
            "word": "地震",
            "read": "じしん",
            "mean": "지진"
        },
        {
            "word": "舌",
            "read": "した",
            "mean": "혀"
        },
        {
            "word": "時代",
            "read": "じだい",
            "mean": "시대"
        },
        {
            "word": "下着",
            "read": "したぎ",
            "mean": "속옷"
        },
        {
            "word": "支度",
            "read": "したく",
            "mean": "준비, 채비"
        },
        {
            "word": "室内",
            "read": "しつない",
            "mean": "실내"
        },
        {
            "word": "失敗",
            "read": "しっぱい",
            "mean": "실패"
        },
        {
            "word": "質問",
            "read": "しつもん",
            "mean": "질문"
        },
        {
            "word": "失礼",
            "read": "しつれい",
            "mean": "실례"
        },
        {
            "word": "辞典",
            "read": "じてん",
            "mean": "사전"
        },
        {
            "word": "自転車",
            "read": "じてんしゃ",
            "mean": "자전거"
        },
        {
            "word": "自動",
            "read": "じどう",
            "mean": "자동"
        },
        {
            "word": "自動車",
            "read": "じどうしゃ",
            "mean": "자동차"
        },
        {
            "word": "市内",
            "read": "しない",
            "mean": "시내"
        }
    ],
    "quiz": [
        {
            "q": "「産業」の読み方は何ですか。",
            "opt": [
                "さんぎょう",
                "さんごう",
                "ざんぎょう",
                "しょくぎょう"
            ],
            "ans": 0,
            "comment": "産業(さんぎょう)는 '산업'을 의미합니다."
        },
        {
            "q": "「事故」の読み方は何ですか。",
            "opt": [
                "じこ",
                "じご",
                "しこ",
                "しご"
            ],
            "ans": 0,
            "comment": "事故(じこ)는 '사고'를 의미합니다."
        },
        {
            "q": "「辞書」と同じ意味の言葉はどれですか。",
            "opt": [
                "辞典",
                "自転車",
                "時代",
                "支度"
            ],
            "ans": 0,
            "comment": "辞典(じてん)은 辞書(じしょ)와 같은 의미로 '사전'을 뜻합니다."
        },
        {
            "q": "「再来年」はいつですか。",
            "opt": [
                "2年後",
                "来年",
                "3年後",
                "今年"
            ],
            "ans": 0,
            "comment": "再来年(さらいねん)은 내년의 다음 해, 즉 '내후년(2년 후)'을 의미합니다."
        },
        {
            "q": "熱いスープを飲んで、（　　）をやけどしました。",
            "opt": [
                "舌",
                "字",
                "味",
                "色"
            ],
            "ans": 0,
            "comment": "뜨거운 것을 마셔서 데일 수 있는 신체 부위는 '舌(した, 혀)'입니다."
        },
        {
            "q": "出かける前に、旅行の（　　）をします。",
            "opt": [
                "支度",
                "失敗",
                "賛成",
                "質問"
            ],
            "ans": 0,
            "comment": "여행을 가기 전에 하는 것은 '支度(したく, 준비/채비)'입니다."
        },
        {
            "q": "「市内」の意味は何ですか。",
            "opt": [
                "시내 (도시 안)",
                "실내",
                "교외",
                "시골"
            ],
            "ans": 0,
            "comment": "市内(しない)는 도시의 안쪽, 즉 '시내'를 의미합니다."
        },
        {
            "q": "「失敗」の読み方は何ですか。",
            "opt": [
                "しっぱい",
                "しつはい",
                "しつばい",
                "じっぱい"
            ],
            "ans": 0,
            "comment": "失敗(しっぱい)는 '실패' 또는 '실수'를 의미합니다. 발음에 주의하세요."
        },
        {
            "q": "自転車で急な（　　）を登るのは大変です。",
            "opt": [
                "坂",
                "板",
                "塩",
                "皿"
            ],
            "ans": 0,
            "comment": "자전거로 오르기 힘든 곳은 '坂(さか, 언덕/비탈)'입니다."
        },
        {
            "q": "「仕方」がないの意味は何ですか。",
            "opt": [
                "방법이 없다 (어쩔 수 없다)",
                "시간이 없다",
                "돈이 없다",
                "일이 없다"
            ],
            "ans": 0,
            "comment": "仕方(しかた)는 '방법'을 뜻하며, 仕方がない는 '방법이 없다', 즉 '어쩔 수 없다'는 관용구입니다."
        }
    ]
}
