{
    "title": "Day 2 단어장",
    "story": null,
    "analysis": [],
    "vocab": [
        {
            "word": "永遠",
            "read": "えいえん",
            "mean": "영원"
        },
        {
            "word": "影響",
            "read": "えいきょう",
            "mean": "영향"
        },
        {
            "word": "英国",
            "read": "えいこく",
            "mean": "영국"
        },
        {
            "word": "英文",
            "read": "えいぶん",
            "mean": "영문"
        },
        {
            "word": "栄養",
            "read": "えいよう",
            "mean": "영양"
        },
        {
            "word": "笑顔",
            "read": "えがお",
            "mean": "웃는 얼굴"
        },
        {
            "word": "宴会",
            "read": "えんかい",
            "mean": "연회, 회식"
        },
        {
            "word": "延期",
            "read": "えんき",
            "mean": "연기"
        },
        {
            "word": "演劇",
            "read": "えんげき",
            "mean": "연극"
        },
        {
            "word": "演奏",
            "read": "えんそう",
            "mean": "연주"
        },
        {
            "word": "遠足",
            "read": "えんそく",
            "mean": "소풍"
        },
        {
            "word": "おい",
            "read": "おい",
            "mean": "조카(남자)"
        },
        {
            "word": "お祝い",
            "read": "おいわい",
            "mean": "축하, 축하 선물"
        },
        {
            "word": "応援",
            "read": "おうえん",
            "mean": "응원"
        },
        {
            "word": "王様",
            "read": "おうさま",
            "mean": "임금님"
        },
        {
            "word": "王子",
            "read": "おうじ",
            "mean": "왕자"
        },
        {
            "word": "横断",
            "read": "おうだん",
            "mean": "횡단"
        },
        {
            "word": "往復",
            "read": "おうふく",
            "mean": "왕복"
        },
        {
            "word": "応募",
            "read": "おうぼ",
            "mean": "응모"
        },
        {
            "word": "応用",
            "read": "おうよう",
            "mean": "응용"
        },
        {
            "word": "大通り",
            "read": "おおどおり",
            "mean": "큰길, 대로"
        },
        {
            "word": "大家",
            "read": "おおや",
            "mean": "집주인"
        },
        {
            "word": "奥",
            "read": "おく",
            "mean": "안쪽, 깊은 곳"
        },
        {
            "word": "屋外",
            "read": "おくがい",
            "mean": "옥외, 야외"
        },
        {
            "word": "屋内",
            "read": "おくない",
            "mean": "옥내, 실내"
        },
        {
            "word": "お小遣い",
            "read": "おこづかい",
            "mean": "용돈"
        },
        {
            "word": "おしまい",
            "read": "おしまい",
            "mean": "끝"
        },
        {
            "word": "おしゃれ",
            "read": "おしゃれ",
            "mean": "멋을 냄, 멋쟁이"
        },
        {
            "word": "お尻",
            "read": "おしり",
            "mean": "엉덩이"
        },
        {
            "word": "お勧め",
            "read": "おすすめ",
            "mean": "추천"
        },
        {
            "word": "お疲れ様",
            "read": "おつかれさま",
            "mean": "수고하셨습니다"
        },
        {
            "word": "お手伝いさん",
            "read": "おてつだいさん",
            "mean": "가정부"
        },
        {
            "word": "お見合い",
            "read": "おみあい",
            "mean": "맞선"
        },
        {
            "word": "親指",
            "read": "おやゆび",
            "mean": "엄지손가락"
        },
        {
            "word": "お礼",
            "read": "おれい",
            "mean": "사례, 감사"
        },
        {
            "word": "音楽家",
            "read": "おんがくか",
            "mean": "음악가"
        },
        {
            "word": "温室",
            "read": "おんしつ",
            "mean": "온실"
        },
        {
            "word": "温泉",
            "read": "おんせん",
            "mean": "온천"
        },
        {
            "word": "温度",
            "read": "おんど",
            "mean": "온도"
        },
        {
            "word": "おんぶ",
            "read": "おんぶ",
            "mean": "어부바, 업음"
        },
        {
            "word": "会員",
            "read": "かいいん",
            "mean": "회원"
        },
        {
            "word": "絵画",
            "read": "かいが",
            "mean": "회화, 그림"
        },
        {
            "word": "海外",
            "read": "かいがい",
            "mean": "해외"
        },
        {
            "word": "会館",
            "read": "かいかん",
            "mean": "회관"
        },
        {
            "word": "解決",
            "read": "かいけつ",
            "mean": "해결"
        },
        {
            "word": "会合",
            "read": "かいごう",
            "mean": "회합, 모임"
        },
        {
            "word": "改札",
            "read": "かいさつ",
            "mean": "개찰"
        },
        {
            "word": "改札口",
            "read": "かいさつぐち",
            "mean": "개찰구"
        },
        {
            "word": "回収",
            "read": "かいしゅう",
            "mean": "회수"
        },
        {
            "word": "外出",
            "read": "がいしゅつ",
            "mean": "외출"
        },
        {
            "word": "外食",
            "read": "がいしょく",
            "mean": "외식"
        },
        {
            "word": "海水浴",
            "read": "かいすいよく",
            "mean": "해수욕"
        },
        {
            "word": "回数",
            "read": "かいすう",
            "mean": "횟수"
        },
        {
            "word": "解説",
            "read": "かいせつ",
            "mean": "해설"
        },
        {
            "word": "会費",
            "read": "かいひ",
            "mean": "회비"
        },
        {
            "word": "香り",
            "read": "かおり",
            "mean": "향기"
        },
        {
            "word": "画家",
            "read": "がか",
            "mean": "화가"
        },
        {
            "word": "価格",
            "read": "かかく",
            "mean": "가격"
        },
        {
            "word": "化学",
            "read": "かがく",
            "mean": "화학"
        },
        {
            "word": "係り",
            "read": "かかり",
            "mean": "담당, 담당자"
        },
        {
            "word": "書留",
            "read": "かきとめ",
            "mean": "등기"
        },
        {
            "word": "書き取り",
            "read": "かきとり",
            "mean": "받아쓰기"
        },
        {
            "word": "家具",
            "read": "かぐ",
            "mean": "가구"
        },
        {
            "word": "各駅停車",
            "read": "かくえきていしゃ",
            "mean": "각 역 정차"
        },
        {
            "word": "覚悟",
            "read": "かくご",
            "mean": "각오"
        },
        {
            "word": "学者",
            "read": "がくしゃ",
            "mean": "학자"
        },
        {
            "word": "学習",
            "read": "がくしゅう",
            "mean": "학습"
        },
        {
            "word": "拡大",
            "read": "かくだい",
            "mean": "확대"
        },
        {
            "word": "各地",
            "read": "かくち",
            "mean": "각지"
        }
    ],
    "quiz": []
}
