{
    "title": "Day 17: 人と動物の数え方 (사람과 동물 세는 법)",
    "story": "<h3>Scene 1. 教室の学生 (교실의 학생)</h3><p>教室に学生が<ruby>何人<rt>なんにん</rt></ruby>いますか。男の学生が<ruby>一人<rt>ひとり</rt></ruby>、<ruby>二人<rt>ふたり</rt></ruby>います。女の学生は<ruby>三人<rt>さんにん</rt></ruby>、<ruby>四人<rt>よにん</rt></ruby>、<ruby>五人<rt>ごにん</rt></ruby>います。先生が来ました。全部で<ruby>六人<rt>ろくにん</rt></ruby>、<ruby>七人<rt>ななにん</rt></ruby>、<ruby>八人<rt>はちにん</rt></ruby>になりました。遅れて<ruby>九人<rt>きゅうにん</rt></ruby>、<ruby>十人<rt>じゅうにん</rt></ruby>集まりました。</p><h3>Scene 2. 公園の猫 (공원의 고양이)</h3><p>公園に猫が<ruby>何匹<rt>なんびき</rt></ruby>いますか。親猫が<ruby>一匹<rt>いっぴき</rt></ruby>と、子猫が<ruby>二匹<rt>にひき</rt></ruby>います。あ、<ruby>三匹<rt>さんびき</rt></ruby>、<ruby>四匹<rt>よんひき</rt></ruby>いました。向こうから<ruby>五匹<rt>ごひき</rt></ruby>目も来ました。</p><h3>Scene 3. 池の金魚 (연못의 금붕어)</h3><p>池の中に金魚がたくさんいます。<ruby>六匹<rt>ろっぴき</rt></ruby>、<ruby>七匹<rt>ななひき</rt></ruby>泳いでいます。赤い魚が<ruby>八匹<rt>はっぴき</rt></ruby>、黒い魚が<ruby>九匹<rt>きゅうひき</rt></ruby>です。全部で<ruby>十匹<rt>じゅっぴき</rt></ruby>以上いますね。</p>",
    "analysis": [
        {
            "sent": "教室に学生が<ruby>何人<rt>なんにん</rt></ruby>いますか。",
            "trans": "교실에 학생이 몇 명 있습니까?",
            "grammar": "何人 (의문사)",
            "tags": [
                "何人"
            ]
        },
        {
            "sent": "男の学生が<ruby>一人<rt>ひとり</rt></ruby>、<ruby>二人<rt>ふたり</rt></ruby>います。",
            "trans": "남학생이 한 명, 두 명 있습니다.",
            "grammar": "사람 세기 (1명: ひとり, 2명: ふたり)",
            "tags": [
                "一人",
                "二人"
            ]
        },
        {
            "sent": "女の学生は<ruby>三人<rt>さんにん</rt></ruby>、<ruby>四人<rt>よにん</rt></ruby>、<ruby>五人<rt>ごにん</rt></ruby>います。",
            "trans": "여학생은 세 명, 네 명, 다섯 명 있습니다.",
            "grammar": "4명: よにん (발음 주의)",
            "tags": [
                "三人",
                "四人",
                "五人"
            ]
        },
        {
            "sent": "全部で<ruby>六人<rt>ろくにん</rt></ruby>、<ruby>七人<rt>ななにん</rt></ruby>、<ruby>八人<rt>はちにん</rt></ruby>になりました。",
            "trans": "전부 해서 여섯 명, 일곱 명, 여덟 명 되었습니다.",
            "grammar": "~になる (변화)",
            "tags": [
                "六人",
                "七人",
                "八人"
            ]
        },
        {
            "sent": "遅れて<ruby>九人<rt>きゅうにん</rt></ruby>、<ruby>十人<rt>じゅうにん</rt></ruby>集まりました。",
            "trans": "늦게 아홉 명, 열 명 모였습니다.",
            "grammar": "사람 세기 (~人)",
            "tags": [
                "九人",
                "十人"
            ]
        },
        {
            "sent": "公園に猫が<ruby>何匹<rt>なんびき</rt></ruby>いますか。",
            "trans": "공원에 고양이가 몇 마리 있습니까?",
            "grammar": "何匹 (의문사)",
            "tags": [
                "何匹"
            ]
        },
        {
            "sent": "親猫が<ruby>一匹<rt>いっぴき</rt></ruby>と、子猫が<ruby>二匹<rt>にひき</rt></ruby>います。",
            "trans": "어미 고양이가 한 마리와, 새끼 고양이가 두 마리 있습니다.",
            "grammar": "동물 세기 (~匹)",
            "tags": [
                "一匹",
                "二匹"
            ]
        },
        {
            "sent": "あ、<ruby>三匹<rt>さんびき</rt></ruby>、<ruby>四匹<rt>よんひき</rt></ruby>いました。",
            "trans": "아, 세 마리, 네 마리 있었습니다.",
            "grammar": "3마리: さんびき (연탁)",
            "tags": [
                "三匹",
                "四匹"
            ]
        },
        {
            "sent": "向こうから<ruby>五匹<rt>ごひき</rt></ruby>目も来ました。",
            "trans": "저쪽에서 다섯 마리째도 왔습니다.",
            "grammar": "~目 (순서)",
            "tags": [
                "五匹"
            ]
        },
        {
            "sent": "<ruby>六匹<rt>ろっぴき</rt></ruby>、<ruby>七匹<rt>ななひき</rt></ruby>泳いでいます。",
            "trans": "여섯 마리, 일곱 마리 헤엄치고 있습니다.",
            "grammar": "6마리: ろっぴき (촉음)",
            "tags": [
                "六匹",
                "七匹"
            ]
        },
        {
            "sent": "赤い魚が<ruby>八匹<rt>はっぴき</rt></ruby>、黒い魚が<ruby>九匹<rt>きゅうひき</rt></ruby>です。",
            "trans": "빨간 물고기가 여덟 마리, 검은 물고기가 아홉 마리입니다.",
            "grammar": "8마리: はっぴき",
            "tags": [
                "八匹",
                "九匹"
            ]
        },
        {
            "sent": "全部で<ruby>十匹<rt>じゅっぴき</rt></ruby>以上いますね。",
            "trans": "전부 해서 열 마리 이상 있군요.",
            "grammar": "10마리: じゅっぴき",
            "tags": [
                "十匹"
            ]
        }
    ],
    "vocab": [
        {
            "word": "一人",
            "read": "ひとり",
            "mean": "한 명"
        },
        {
            "word": "二人",
            "read": "ふたり",
            "mean": "두 명"
        },
        {
            "word": "三人",
            "read": "さんにん",
            "mean": "세 명"
        },
        {
            "word": "四人",
            "read": "よにん",
            "mean": "네 명"
        },
        {
            "word": "五人",
            "read": "ごにん",
            "mean": "다섯 명"
        },
        {
            "word": "六人",
            "read": "ろくにん",
            "mean": "여섯 명"
        },
        {
            "word": "七人",
            "read": "ななにん",
            "mean": "일곱 명"
        },
        {
            "word": "八人",
            "read": "はちにん",
            "mean": "여덟 명"
        },
        {
            "word": "九人",
            "read": "きゅうにん",
            "mean": "아홉 명"
        },
        {
            "word": "十人",
            "read": "じゅうにん",
            "mean": "열 명"
        },
        {
            "word": "何人",
            "read": "なんにん",
            "mean": "몇 명"
        },
        {
            "word": "一匹",
            "read": "いっぴき",
            "mean": "한 마리"
        },
        {
            "word": "二匹",
            "read": "にひき",
            "mean": "두 마리"
        },
        {
            "word": "三匹",
            "read": "さんびき",
            "mean": "세 마리"
        },
        {
            "word": "四匹",
            "read": "よんひき",
            "mean": "네 마리"
        },
        {
            "word": "五匹",
            "read": "ごひき",
            "mean": "다섯 마리"
        },
        {
            "word": "六匹",
            "read": "ろっぴき",
            "mean": "여섯 마리"
        },
        {
            "word": "七匹",
            "read": "ななひき",
            "mean": "일곱 마리"
        },
        {
            "word": "八匹",
            "read": "はっぴき",
            "mean": "여덟 마리"
        },
        {
            "word": "九匹",
            "read": "きゅうひき",
            "mean": "아홉 마리"
        },
        {
            "word": "十匹",
            "read": "じゅっぴき",
            "mean": "열 마리"
        },
        {
            "word": "何匹",
            "read": "なんびき",
            "mean": "몇 마리"
        }
    ],
    "quiz": [
        {
            "q": "「一人」の読み方は何ですか。",
            "opt": [
                "いちにん",
                "ひとり",
                "いちじん",
                "ひとつ"
            ],
            "ans": 1,
            "comment": "一人은 'ひとり'라고 읽습니다."
        },
        {
            "q": "「二人」の読み方は何ですか。",
            "opt": [
                "ににん",
                "ふたり",
                "にじん",
                "ふたつ"
            ],
            "ans": 1,
            "comment": "二人은 'ふたり'라고 읽습니다."
        },
        {
            "q": "「三匹」の読み方は何ですか。",
            "opt": [
                "さんひき",
                "さんびき",
                "さんぴき",
                "みっひき"
            ],
            "ans": 1,
            "comment": "三匹는 연탁 현상으로 'さんびき'라고 읽습니다."
        },
        {
            "q": "「四人」の読み方は何ですか。",
            "opt": [
                "よにん",
                "よんにん",
                "しにん",
                "よったり"
            ],
            "ans": 0,
            "comment": "四人은 'よにん'이라고 읽습니다. 'ん'이 들어가지 않도록 주의하세요."
        },
        {
            "q": "「六匹」の読み方は何ですか。",
            "opt": [
                "ろくひき",
                "ろっぴき",
                "むっひき",
                "ろくびき"
            ],
            "ans": 1,
            "comment": "六匹는 'ろっぴき'라고 읽습니다. (반탁음/촉음)"
        },
        {
            "q": "「一匹」の読み方は何ですか。",
            "opt": [
                "いちひき",
                "いっぴき",
                "いちびき",
                "ひとひき"
            ],
            "ans": 1,
            "comment": "一匹는 'いっぴき'라고 읽습니다."
        },
        {
            "q": "猫や犬を数えるときに使う言葉は何ですか。",
            "opt": [
                "人",
                "枚",
                "匹",
                "冊"
            ],
            "ans": 2,
            "comment": "고양이나 개 같은 작은 동물은 '匹(ひき)'로 셉니다."
        },
        {
            "q": "「何人」の意味は何ですか。",
            "opt": [
                "몇 마리",
                "몇 명",
                "몇 개",
                "몇 살"
            ],
            "ans": 1,
            "comment": "何人(なんにん)은 사람 수를 물을 때 쓰는 '몇 명'입니다."
        },
        {
            "q": "「九人」の読み方は何ですか。",
            "opt": [
                "くにん",
                "きゅうにん",
                "ここのにん",
                "くうにん"
            ],
            "ans": 1,
            "comment": "九人은 'きゅうにん'이라고 읽습니다."
        },
        {
            "q": "「十匹」の読み方は何ですか。",
            "opt": [
                "じゅうひき",
                "じゅっぴき",
                "とおひき",
                "じゅうびき"
            ],
            "ans": 1,
            "comment": "十匹는 'じゅっぴき'라고 읽습니다."
        }
    ]
}
